<?xml version="1.0" encoding="UTF-8" ?>
<dt-example table-type="html" order="6" framework="jqueryui">

<css lib="datatables autofill"/>
<js lib="jquery datatables autofill">
<![CDATA[
$('#example').DataTable( {
	autoFill: true
} );
]]>
</js>

<js-vanilla>
<![CDATA[
new DataTable('#example', {
	autoFill: true
} );
]]>
</js-vanilla>

<title lib="AutoFill">jQuery UI styling</title>

<info><![CDATA[

This example shows DataTables and AutoFill being used with [jQuery UI](http://jqueryui.com/) providing the base styling information.

]]></info>

</dt-example>

